exasol/nb_connector/ai_lab_config.py
exasol/nb_connector/bfs_connection.py
exasol/nb_connector/bfs_utils.py
exasol/nb_connector/cli/commands/__init__.py
exasol/nb_connector/cli/commands/check.py
exasol/nb_connector/cli/commands/configure.py
exasol/nb_connector/cli/commands/show.py
exasol/nb_connector/cli/groups.py
exasol/nb_connector/cli/main.py
exasol/nb_connector/cli/options/__init__.py
exasol/nb_connector/cli/options/bucketfs.py
exasol/nb_connector/cli/options/common.py
exasol/nb_connector/cli/options/docker_db.py
exasol/nb_connector/cli/options/onprem.py
exasol/nb_connector/cli/options/saas.py
exasol/nb_connector/cli/options/ssl.py
exasol/nb_connector/cli/param_wrappers.py
exasol/nb_connector/cli/processing/backend_selector.py
exasol/nb_connector/cli/processing/bucketfs_access.py
exasol/nb_connector/cli/processing/option_set.py
exasol/nb_connector/cli/processing/processing.py
exasol/nb_connector/cli/reporting.py
exasol/nb_connector/cloud_storage.py
exasol/nb_connector/connections.py
exasol/nb_connector/container_by_ip.py
exasol/nb_connector/extension_wrapper_common.py
exasol/nb_connector/github.py
exasol/nb_connector/itde_manager.py
exasol/nb_connector/language_container_activation.py
exasol/nb_connector/model_installation.py
exasol/nb_connector/sagemaker_extension_wrapper.py
exasol/nb_connector/secret_store.py
exasol/nb_connector/slc/__init__.py
exasol/nb_connector/slc/constants.py
exasol/nb_connector/slc/script_language_container.py
exasol/nb_connector/slc/slc_compression_strategy.py
exasol/nb_connector/slc/slc_error.py
exasol/nb_connector/slc/slc_flavor.py
exasol/nb_connector/slc/workspace.py
exasol/nb_connector/text_ai_extension_wrapper.py
exasol/nb_connector/transformers_extension_wrapper.py
exasol/nb_connector/utils.py
exasol_notebook_connector-2.2.0.dist-info/LICENSE
exasol_notebook_connector-2.2.0.dist-info/METADATA
exasol_notebook_connector-2.2.0.dist-info/WHEEL
exasol_notebook_connector-2.2.0.dist-info/entry_points.txt
exasol_notebook_connector-2.2.0.dist-info/RECORD
