Metadata-Version: 2.3
Name: exasol-notebook-connector
Version: 2.2.0
Summary: Components, tools, APIs, and configurations in order to connect Jupyter notebooks to Exasol and various other systems.
License: MIT
Author: Christoph Kuhnke
Author-email: christoph.kuhnke@exasol.com
Maintainer: Christoph Kuhnke
Maintainer-email: christoph.kuhnke@exasol.com
Requires-Python: >=3.10,<3.13
Classifier: Development Status :: 3 - Alpha
Classifier: Framework :: Jupyter :: JupyterLab :: 3
Classifier: License :: OSI Approved :: MIT License
Classifier: Programming Language :: Python :: 3
Classifier: Programming Language :: Python :: 3.10
Classifier: Programming Language :: Python :: 3.11
Classifier: Programming Language :: Python :: 3.12
Classifier: Topic :: Security :: Cryptography
Provides-Extra: bucketfs
Provides-Extra: docker-db
Provides-Extra: ibis
Provides-Extra: pyexasol
Provides-Extra: sagemaker
Provides-Extra: slc
Provides-Extra: sqlalchemy
Provides-Extra: text-ai
Provides-Extra: transformers
Requires-Dist: GitPython (>=2.1.0) ; extra == "slc"
Requires-Dist: exasol-bucketfs (>=1.0.1,<3) ; extra == "bucketfs"
Requires-Dist: exasol-integration-test-docker-environment (>=4,<5) ; extra == "docker-db"
Requires-Dist: exasol-saas-api (>=0.9.0,<3)
Requires-Dist: exasol-sagemaker-extension (>=0.11.5) ; extra == "sagemaker"
Requires-Dist: exasol-script-languages-container-tool (>=3,<4) ; extra == "slc"
Requires-Dist: exasol-text-ai-extension (>=0.1.0,<2.0.0) ; extra == "text-ai"
Requires-Dist: exasol-transformers-extension (>=2.2.1,<3) ; extra == "transformers"
Requires-Dist: ibis-framework[exasol] (>=9.1.0,<10) ; extra == "ibis"
Requires-Dist: ifaddr (>=0.2.0,<0.3) ; extra == "docker-db"
Requires-Dist: pyexasol (>=0.26.0,<1) ; extra == "pyexasol"
Requires-Dist: sqlalchemy-exasol (>=5.0.0,<6) ; extra == "sqlalchemy"
Requires-Dist: sqlcipher3 (>=0.5.0) ; sys_platform == "darwin" or sys_platform == "win32"
Requires-Dist: sqlcipher3-binary (>=0.5.0) ; sys_platform == "linux"
Requires-Dist: yaspin (>=3.1.0,<4) ; extra == "transformers"
Project-URL: Documentation, https://github.io/exasol/notebook-connector
Project-URL: Homepage, https://github.io/exasol/notebook-connector
Project-URL: Issues, https://github.io/exasol/notebook-connector/issues
Project-URL: Source, https://github.io/exasol/notebook-connector
